chatads_mcp_wrapper.py
chatads_mcp_wrapper-0.1.11.dist-info/licenses/LICENSE
chatads_mcp_wrapper-0.1.11.dist-info/METADATA
chatads_mcp_wrapper-0.1.11.dist-info/WHEEL
chatads_mcp_wrapper-0.1.11.dist-info/entry_points.txt
chatads_mcp_wrapper-0.1.11.dist-info/top_level.txt
chatads_mcp_wrapper-0.1.11.dist-info/RECORD
