Metadata-Version: 2.4
Name: chatads-mcp-wrapper
Version: 0.1.11
Summary: Model Context Protocol (MCP) wrapper for ChatAds Affiliate API with async support
Author-email: ChatAds Team <support@chatads.com>
License: MIT License
Project-URL: Homepage, https://github.com/chatads/chatads-mcp-wrapper
Project-URL: Documentation, https://github.com/chatads/chatads-mcp-wrapper#readme
Project-URL: Repository, https://github.com/chatads/chatads-mcp-wrapper
Project-URL: Issues, https://github.com/chatads/chatads-mcp-wrapper/issues
Project-URL: Changelog, https://github.com/chatads/chatads-mcp-wrapper/blob/main/CHANGELOG.md
Keywords: mcp,chatads,affiliate,ai,claude,async,model-context-protocol
Classifier: Development Status :: 4 - Beta
Classifier: Intended Audience :: Developers
Classifier: License :: OSI Approved :: MIT License
Classifier: Programming Language :: Python :: 3
Classifier: Programming Language :: Python :: 3.10
Classifier: Programming Language :: Python :: 3.11
Classifier: Programming Language :: Python :: 3.12
Classifier: Programming Language :: Python :: 3.13
Classifier: Topic :: Software Development :: Libraries :: Python Modules
Classifier: Topic :: Internet :: WWW/HTTP
Classifier: Topic :: Internet :: WWW/HTTP :: Dynamic Content
Classifier: Framework :: AsyncIO
Classifier: Typing :: Typed
Requires-Python: >=3.10
License-File: LICENSE
Requires-Dist: fastmcp>=0.4.1
Requires-Dist: httpx>=0.27.2
Requires-Dist: pydantic>=2.12.0
Requires-Dist: python-json-logger>=2.0.7
Provides-Extra: dev
Requires-Dist: pytest>=8.3.3; extra == "dev"
Requires-Dist: pytest-cov>=6.0.0; extra == "dev"
Requires-Dist: pytest-asyncio>=0.24.0; extra == "dev"
Requires-Dist: pytest-httpx>=0.35.0; extra == "dev"
Requires-Dist: black>=24.10.0; extra == "dev"
Requires-Dist: ruff>=0.8.4; extra == "dev"
Requires-Dist: mypy>=1.13.0; extra == "dev"
Dynamic: license-file
